<?xml version="1.0" encoding="UTF-8"?>
<!--
  Copyright 2007 University of Oxford

  Licensed under the Apache License, Version 2.0 (the "License");
  you may not use this file except in compliance with the License.
  You may obtain a copy of the License at

      http://www.apache.org/licenses/LICENSE-2.0

  Unless required by applicable law or agreed to in writing, software
  distributed under the License is distributed on an "AS IS" BASIS,
  WITHOUT WARRANTIES OR CONDITIONS OF ANY KIND, either express or implied.
  See the License for the specific language governing permissions and
  limitations under the License.
-->
<!--
Forrest site.xml

This file contains an outline of the site's information content.  It is used to:
- Generate the website menus (though these can be overridden - see docs)
- Provide semantic, location-independent aliases for internal 'site:' URIs, eg
<link href="site:changes"> links to changes.html (or ../changes.html if in
  subdir).
- Provide aliases for external URLs in the external-refs section.  Eg, <link
  href="ext:cocoon"> links to http://cocoon.apache.org/ 

See http://forrest.apache.org/docs/linking.html for more info
-->

<!-- The label attribute of the outer "site" element will only show
  in the linkmap (linkmap.html).
  Use elements project-name and group-name in skinconfig to change name of 
  your site or project that is usually shown at the top of page.
  No matter what you configure for the href attribute, Forrest will
  always use index.html when you request http://yourHost/
  See FAQ: "How can I use a start-up-page other than index.html?"
-->

<site label="Simal" href=""  tab=""
  xmlns="http://apache.org/forrest/linkmap/1.0"
  xmlns:xi="http://www.w3.org/2001/XInclude">
  <about label="About" tab="home">
    <index label="Home" href="index.html" description="Welcome to Simal"/>
    <overview label="Overview" href="overview.html" description="Overview of the Simal project"/>
    <quickstart label="Quick Start" href="quickstart.html" description="The minimum you need to get started"/>
    <gettingSimal label="Getting Simal" href="gettingSimal.html" description="How to get the Simal application(s)"/>
    <changes label="Changes" href="changes.html" description="Recent changes"/>
    <changes-rss href="/changes.rss"/>
    <!--<simalCommunity label="Community" href="developingCommunity.html" description="How is the Simal community structured?"/>-->
    <whySimal label="Why Simal?" href="whySimal.html" description="What does the name Simal mean?"/>
    <credits label="Credits" href="credits.html" description="Simal would not exist without these people..."/>
  </about>
  
  <users label="Using Simal" href="user/" tab="user">
    <index label="About" href="index.html"/>
  </users>
  
  <contributors label="Contributors" href="contributor/" tab="contributor">
    <index label="Index" href="index.html"/>
    
    <issueTracker label="Issue Tracking" href="issueTracking.html" description="A description of how we use our issue tracker"/>
    
    <governance label="Governance" href="governance/">
      <model label="Project Management" href="index.html" description="Description of the project management rules of the Simal project"/>
      <newCommitters label="New Committers" href="newCommitters.html" description="Actions that need to be taken by new committers"/>
    </governance>

    <developSimal label="Development Environment" href="developSimal.html" description="How to get started on developing Simal"/>    
    
    <documentationStructure label="Documentation Structure" href="documentationStructure.html"/>
    
  </contributors>

  <coreModule label="Simal Core" tab="contributor" href="core/">
    <xi:include href="cocoon://core/site.xml"/>
  </coreModule>

  <restModule label="Simal REST" tab="contributor" href="rest/">
    <xi:include href="cocoon://rest/site.xml"/>
  </restModule>

  <restModule label="Simal Web Module" tab="contributor" href="web/">
    <xi:include href="cocoon://web/site.xml"/>
  </restModule>
  
  <userResources label="Users" tab="home">  
    <userDocs label="User Docs" href="user/index.html"/>
    <userMailingList label="Mailing List" href="ext:simal/userList"/>
  </userResources> 
  
  <contributorResources label="Contributors" tab="home">    
    <devDocs label="Contributor Docs" href="contributor/index.html"/>
    <devSite label="Developer Site" href="ext:simal/devSite"/>
    <devMailingList label="Mailing List" href="ext:simal/devList"/>
    <issueTracker label="Issue Tracker" href="ext:simal/issueTracker"/>
    <svn label="SVN" href="ext:simal/svn"/>
  </contributorResources>
      
  <external-refs>
    <forrest href="http://forrest.apache.org/">
      <linking href="docs/linking.html"/>
    </forrest>
    <simal href="http://simal.oss-watch.ac.uk">
      <projectSite href="http://simal.oss-watch.ac.uk/"/>
      <coreModule href="core/">
        <download href="download.html"/>
      </coreModule>
      <restModule href="http://simal.oss-watch.ac.uk/rest"/>
      <webModule href="http://simal.oss-watch.ac.uk/web"/>
      <demoSite href="http://data.oss-watch.ac.uk:8080/"/>
      <devSite href="http://code.google.com/p/simal"/>
      <devList href="http://groups.google.com/group/simal-contributors"/>
      <userList href="http://groups.google.com/group/simal-contributors"/>
      <issueTracker href="http://code.google.com/p/simal/issues/list"/>
      <svn href="http://code.google.com/p/simal/source"/>
      <wiki href="http://code.google.com/p/simal/w/list"/>
    </simal>
  </external-refs>

</site>
